opttech/__init__.py
opttech/core/__init__.py
opttech/excel_tools/__init__.py
opttech/excel_tools/excel_conversion.py
opttech/parameters/__init__.py
opttech/parameters/constants.py
opttech/parameters/defaults.py
opttech/parameters/env_config.py
opttech/parameters/sped/constants.py
opttech/parameters/sped/sped_rules/ECD - LEIAUTE_0001 - VERSAO_2009.json
opttech/parameters/sped/sped_rules/ECD - LEIAUTE_0001 - VERSAO_2010.json
opttech/parameters/sped/sped_rules/ECD - LEIAUTE_0001 - VERSAO_2011.json
opttech/parameters/sped/sped_rules/ECD - LEIAUTE_0001 - VERSAO_2012.json
opttech/parameters/sped/sped_rules/ECD - LEIAUTE_0002 - VERSAO_2013.json
opttech/parameters/sped/sped_rules/ECD - LEIAUTE_0003 - VERSAO_2014.json
opttech/parameters/sped/sped_rules/ECD - LEIAUTE_0004 - VERSAO_2015.json
opttech/parameters/sped/sped_rules/ECD - LEIAUTE_0005 - VERSAO_2016.json
opttech/parameters/sped/sped_rules/ECD - LEIAUTE_0006 - VERSAO_2017.json
opttech/parameters/sped/sped_rules/ECD - LEIAUTE_0007 - VERSAO_2018.json
opttech/parameters/sped/sped_rules/ECD - LEIAUTE_0008 - VERSAO_2019.json
opttech/parameters/sped/sped_rules/ECD - LEIAUTE_0009 - VERSAO_2020.json
opttech/parameters/sped/sped_rules/ECD - LEIAUTE_0009 - VERSAO_2021.json
opttech/parameters/sped/sped_rules/ECD - LEIAUTE_0009 - VERSAO_2022.json
opttech/parameters/sped/sped_rules/ECD - LEIAUTE_0009 - VERSAO_2023.json
opttech/parameters/sped/sped_rules/ECD - LEIAUTE_0009 - VERSAO_2024.json
opttech/parameters/sped/sped_rules/ECF - LEIAUTE_0001.json
opttech/parameters/sped/sped_rules/ECF - LEIAUTE_0002.json
opttech/parameters/sped/sped_rules/ECF - LEIAUTE_0003.json
opttech/parameters/sped/sped_rules/ECF - LEIAUTE_0004.json
opttech/parameters/sped/sped_rules/ECF - LEIAUTE_0005.json
opttech/parameters/sped/sped_rules/ECF - LEIAUTE_0006.json
opttech/parameters/sped/sped_rules/ECF - LEIAUTE_0007.json
opttech/parameters/sped/sped_rules/ECF - LEIAUTE_0008.json
opttech/parameters/sped/sped_rules/ECF - LEIAUTE_0009.json
opttech-1.3.2.dist-info/LICENSE
opttech-1.3.2.dist-info/METADATA
opttech-1.3.2.dist-info/WHEEL
opttech-1.3.2.dist-info/RECORD
