Metadata-Version: 2.3
Name: opttech
Version: 1.3.2
Summary: Biblioteca desenvolvida e mantida pela OptTech.
License: MIT
Keywords: OptTech
Author: Eduardo Anacleto
Author-email: contato@opttech.com.br
Requires-Python: >=3.10
Classifier: License :: OSI Approved :: MIT License
Classifier: Programming Language :: Python :: 3
Classifier: Programming Language :: Python :: 3.10
Classifier: Programming Language :: Python :: 3.11
Classifier: Programming Language :: Python :: 3.12
Classifier: Programming Language :: Python :: 3.13
Requires-Dist: asn1crypto (>=1.5.1,<2.0.0)
Requires-Dist: charset-normalizer (>=3.4.2,<4.0.0)
Requires-Dist: openpyxl (>=3.1.5,<4.0.0)
Requires-Dist: polars (>=1.30.0,<2.0.0)
Requires-Dist: py7zr (>=0.22.0,<0.23.0)
Requires-Dist: pyarrow (>=20.0.0,<21.0.0)
Requires-Dist: rarfile (>=4.2,<5.0)
Requires-Dist: tqdm (>=4.67.1,<5.0.0)
Requires-Dist: unidecode (>=1.4.0,<2.0.0)
Requires-Dist: xlsxwriter (>=3.2.3,<4.0.0)
